Workbook

Sheet Instructions
A1: There are three steps to using this spreadsheet:
A3: (1) Make assumptions about operations in the Operations worksheet.
A4: (2) Make assumptions about financing in the Financing worksheet.
A5: (3) Use the Solver in the Financing worksheet to minimize bank notes payable subject
A6: to maintaining the minimum cash balance required. This step is explained in the
A7: Financing worksheet.
A9: The only cells that should be changed are in the Operations Assumptions and Financing
A10: Assumptions sections. The spreadsheet will generate income statements, balance
A11: sheets, and statements of cash flows.
A14: Kerry Back
A15: John M. Olin School of Business
A16: 35443

Sheet Operations
A1: OPERATIONS AND INVESTMENTS ASSUMPTIONS
A4: Year | B4: 0 | C4: 1 | D4: 2 | E4: 3 | F4: 4
A6: Sales | C6: 400 | D6: 600 | E6: 800 | F6: 900
A7: COGS (% of sales) | C7: 0.5 | D7: 0.5 | E7: 0.5 | F7: 0.5
A8: SG&A (% of sales) | C8: 0.3 | D8: 0.3 | E8: 0.3
A9: Income tax rate | C9: 0.4 | D9: 0.4 | E9: 0.4
A11: Inventory (% of COGS) | B11: 0.1 | C11: 0.1 | D11: 0.1 | E11: 0.1
A12: Minimum cash balance (% of sales) | B12: 0.04 | C12: 0.04 | D12: 0.04 | E12: 0.04
A13: Accounts receivable (% of sales) | B13: 0.12 | C13: 0.12 | D13: 0.12 | E13: 0.12
A14: Accounts payable (% of COGS) | B14: 0.08 | C14: 0.08 | D14: 0.08 | E14: 0.08
A16: Investment in PP&E | B16: 400 | C16: 100 | D16: 100 | E16: 100
A17: Depreciation | B17: 0 | C17: 100 | D17: 100 | E17: 100
A20: OPERATIONS AND INVESTMENTS CALCULATIONS
A22: Year | B22: 0 | C22: 1 | D22: 2 | E22: 3
A24: Average sales | B24: =0.5*B6+0.5*C6 -> 200 | C24: =0.5*C6+0.5*D6 -> 500 | D24: =0.5*D6+0.5*E6 -> 700 | E24: =0.5*E6+0.5*F6 -> 850
A25: Average COGS | B25: =0.5*B6*B7+0.5*C6*C7 -> 100 | C25: =0.5*C6*C7+0.5*D6*D7 -> 250 | D25: =0.5*D6*D7+0.5*E6*E7 -> 350 | E25: =0.5*E6*E7+0.5*F6*F7 -> 425
A26: Inventory | B26: =B11*B25 -> 10 | C26: =C11*C25 -> 25 | D26: =D11*D25 -> 35 | E26: =E11*E25 -> 42.5
A27: Minimum cash balance | B27: =B12*B24 -> 8 | C27: =C12*C24 -> 20 | D27: =D12*D24 -> 28 | E27: =E12*E24 -> 34
A28: Accounts receivable | B28: 0 | C28: =C13*C24 -> 60 | D28: =D13*D24 -> 84 | E28: =E13*E24 -> 102
A29: Accounts payable | B29: =B14*B25 -> 8 | C29: =C14*C25 -> 20 | D29: =D14*D25 -> 28 | E29: =E14*E25 -> 34
A31: Note: There is a timing issue when comparing a balance sheet to an income statement,
A32: because the balance sheet is at a point in time whereas the income statement is cumulative
A33: over the preceding year. It is most natural to predict assets and liabilities based on the
A34: average of the income statement items over the same (=preceding) year and the following
A35: year.

Sheet Financing
A1: FINANCING ASSUMPTIONS
A4: Interest rate on long-term debt | B4: 0.11
A5: Interest rate on notes payable | B5: 0.09
A7: Year | B7: 0 | C7: 1 | D7: 2 | E7: 3
A9: Long-term debt outstanding | B9: 200 | C9: 200 | D9: 200 | E9: 200
A10: Bank notes payable | B10: 0 | C10: 28.272251 | D10: 68.632987 | E10: 62.012012
A12: Net new equity capital raised | B12: 300 | C12: 0 | D12: 0 | E12: 0
A13: Dividends paid (as positive number) | C13: 0 | D13: 0 | E13: 0
A16: FINANCING CALCULATIONS
A18: Interest Expense
A20: Year | B20: 0 | C20: 1 | D20: 2 | E20: 3
A22: Long-term debt | C22: =$B$4*(B9+C9)/2 -> 22 | D22: =$B$4*(C9+D9)/2 -> 22 | E22: =$B$4*(D9+E9)/2 -> 22
A23: Bank notes payable | C23: =$B$5*(B10+C10)/2 -> 1.2722513 | D23: =$B$5*(C10+D10)/2 -> 4.3607357 | E23: =$B$5*(D10+E10)/2 -> 5.879025
A24: Total | C24: =C22+C23 -> 23.272251 | D24: =D22+D23 -> 26.360736 | E24: =E22+E23 -> 27.879025
A26: Cash Balance
A28: Year | B28: 0 | C28: 1 | D28: 2 | E28: 3
A30: Beginning cash balance | B30: 0 | C30: =B32 -> 98 | D30: =C32 -> 20 | E30: =D32 -> 28
A31: Plus cash flow from ops, invests, and fin | B31: ='Cash flows'!B18 -> 98 | C31: ='Cash flows'!C18 -> -78 | D31: ='Cash flows'!D18 -> 8 | E31: ='Cash flows'!E18 -> 6
A32: Ending cash balance | B32: =B30+B31 -> 98 | C32: =C30+C31 -> 20 | D32: =D30+D31 -> 28 | E32: =E30+E31 -> 34
A33: Less minimum cash balance required | B33: =-Operations!B27 -> -8 | C33: =-Operations!C27 -> -20 | D33: =-Operations!D27 -> -28 | E33: =-Operations!E27 -> -34
A34: Excess cash | B34: =B32+B33 -> 90 | C34: =C32+C33 -> 0 | D34: =D32+D33 -> 0 | E34: =E32+E33 -> 0
A36: It is undesirable to hold excess cash when there are bank notes outstanding.
A37: The cash should be used to reduce the bank loan. To do this, minimize the
A38: present value of the interest expense subject to excess cash being
A39: nonnegative. Click on Solver (from the Tools menu), click on Solve in the next box
A40: that appears, and click on OK in the next box.
A42: Present value of interest on bank notes | B42: =NPV(B5,C23:E23) -> 9.377233

Sheet Income
A1: INCOME STATEMENTS
A3: Year | B3: 0 | C3: 1 | D3: 2 | E3: 3
A5: Sales | C5: =Operations!C6 -> 400 | D5: =Operations!D6 -> 600 | E5: =Operations!E6 -> 800
A6: Less COGS | C6: =-Operations!C7*Operations!C6 -> -200 | D6: =-Operations!D7*Operations!D6 -> -300 | E6: =-Operations!E7*Operations!E6 -> -400
A7: Gross profit | C7: =C5+C6 -> 200 | D7: =D5+D6 -> 300 | E7: =E5+E6 -> 400
A8: Less SG&A expenses | C8: =-Operations!C8*Operations!C6 -> -120 | D8: =-Operations!D8*Operations!D6 -> -180 | E8: =-Operations!E8*Operations!E6 -> -240
A9: Less depreciation | C9: =-Operations!C17 -> -100 | D9: =-Operations!D17 -> -100 | E9: =-Operations!E17 -> -100
A10: Earnings before interest and taxes | C10: =SUM(C7:C9) -> -20 | D10: =SUM(D7:D9) -> 20 | E10: =SUM(E7:E9) -> 60
A11: Less interest expense | C11: =-Financing!C24 -> -23.272251 | D11: =-Financing!D24 -> -26.360736 | E11: =-Financing!E24 -> -27.879025
A12: Pre-tax income | C12: =C10+C11 -> -43.272251 | D12: =D10+D11 -> -6.3607357 | E12: =E10+E11 -> 32.120975
A14: Cumulative pre-tax income (NOL) | C14: =C12 -> -43.272251 | D14: =C14+D12 -> -49.632987 | E14: =D14+E12 -> -17.512012
A15: Taxes | C15: =IF(B14>=0,MAX(Operations!C9*Income!C12,-Operations!C9*Income!B14),MAX(0,Operations!C9*(Income!C12+Income!B14))) -> 0 | D15: =IF(C14>=0,MAX(Operations!D9*Income!D12,-Operations!D9*Income!C14),MAX(0,Operations!D9*(Income!D12+Income!C14))) -> 0 | E15: =IF(D14>=0,MAX(Operations!E9*Income!E12,-Operations!E9*Income!D14),MAX(0,Operations!E9*(Income!E12+Income!D14))) -> 0
A17: Pre-tax income | C17: =C12 -> -43.272251 | D17: =D12 -> -6.3607357 | E17: =E12 -> 32.120975
A18: Less taxes | C18: =-C15 -> 0 | D18: =-D15 -> 0 | E18: =-E15 -> 0
A19: Net income | C19: =C17+C18 -> -43.272251 | D19: =D17+D18 -> -6.3607357 | E19: =E17+E18 -> 32.120975
A21: Note: Net operating losses can be carried forward or backwards. There is a limit on the
A22: number of years they can be carried forward or backwards, but this is not incorporated
A23: into the spreadsheet.

Sheet Balance sheet
A1: BALANCE SHEETS
A4: Year | B4: 0 | C4: 1 | D4: 2 | E4: 3
A6: Cash | B6: =Financing!B32 -> 98 | C6: =Financing!C32 -> 20 | D6: =Financing!D32 -> 28 | E6: =Financing!E32 -> 34
A7: Inventory | B7: =Operations!B26 -> 10 | C7: =Operations!C26 -> 25 | D7: =Operations!D26 -> 35 | E7: =Operations!E26 -> 42.5
A8: Accounts receivable | B8: =Operations!B28 -> 0 | C8: =Operations!C28 -> 60 | D8: =Operations!D28 -> 84 | E8: =Operations!E28 -> 102
A9: Total current assets | B9: =SUM(B6:B8) -> 108 | C9: =SUM(C6:C8) -> 105 | D9: =SUM(D6:D8) -> 147 | E9: =SUM(E6:E8) -> 178.5
A11: Gross property, plant & equipment | B11: =Operations!B16 -> 400 | C11: =B11+Operations!C16 -> 500 | D11: =C11+Operations!D16 -> 600 | E11: =D11+Operations!E16 -> 700
A12: Less accumulated depreciation | B12: =-Operations!B17 -> 0 | C12: =B12-Operations!C17 -> -100 | D12: =C12-Operations!D17 -> -200 | E12: =D12-Operations!E17 -> -300
A13: Net property, plant & equipment | B13: =B11+B12 -> 400 | C13: =C11+C12 -> 400 | D13: =D11+D12 -> 400 | E13: =E11+E12 -> 400
A15: Total assets | B15: =B9+B13 -> 508 | C15: =C9+C13 -> 505 | D15: =D9+D13 -> 547 | E15: =E9+E13 -> 578.5
A17: Accounts payable | B17: =Operations!B29 -> 8 | C17: =Operations!C29 -> 20 | D17: =Operations!D29 -> 28 | E17: =Operations!E29 -> 34
A18: Bank notes payable | B18: =Financing!B10 -> 0 | C18: =Financing!C10 -> 28.272251 | D18: =Financing!D10 -> 68.632987 | E18: =Financing!E10 -> 62.012012
A19: Total current liabilities | B19: =B17+B18 -> 8 | C19: =C17+C18 -> 48.272251 | D19: =D17+D18 -> 96.632987 | E19: =E17+E18 -> 96.012012
A21: Long-term debt | B21: =Financing!B9 -> 200 | C21: =Financing!C9 -> 200 | D21: =Financing!D9 -> 200 | E21: =Financing!E9 -> 200
A22: Shareholders equity | B22: =Financing!B12-Financing!B13 -> 300 | C22: =B22+Financing!C12-Financing!C13+Income!C19 -> 256.72775 | D22: =C22+Financing!D12-Financing!D13+Income!D19 -> 250.36701 | E22: =D22+Financing!E12-Financing!E13+Income!E19 -> 282.48799
A23: Total long-term debt and shareholders equity | B23: =B21+B22 -> 500 | C23: =C21+C22 -> 456.72775 | D23: =D21+D22 -> 450.36701 | E23: =E21+E22 -> 482.48799
A25: Total liabilities | B25: =B19+B23 -> 508 | C25: =C19+C23 -> 505 | D25: =D19+D23 -> 547 | E25: =E19+E23 -> 578.5

Sheet Cash flows
A1: STATEMENTS OF CASH FLOWS
A4: Year | B4: 0 | C4: 1 | D4: 2 | E4: 3
A6: Net income | C6: =Income!C19 -> -43.272251 | D6: =Income!D19 -> -6.3607357 | E6: =Income!E19 -> 32.120975
A7: Plus depreciation | C7: =Operations!C17 -> 100 | D7: =Operations!D17 -> 100 | E7: =Operations!E17 -> 100
A8: Less increase in inventory | B8: =-'Balance sheet'!B7 -> -10 | C8: =-('Balance sheet'!C7-'Balance sheet'!B7) -> -15 | D8: =-('Balance sheet'!D7-'Balance sheet'!C7) -> -10 | E8: =-('Balance sheet'!E7-'Balance sheet'!D7) -> -7.5
A9: Less increase in accounts receivable | B9: =-'Balance sheet'!B8 -> 0 | C9: =-('Balance sheet'!C8-'Balance sheet'!B8) -> -60 | D9: =-('Balance sheet'!D8-'Balance sheet'!C8) -> -24 | E9: =-('Balance sheet'!E8-'Balance sheet'!D8) -> -18
A10: Plus increase in accounts payable | B10: ='Balance sheet'!B17 -> 8 | C10: ='Balance sheet'!C17-'Balance sheet'!B17 -> 12 | D10: ='Balance sheet'!D17-'Balance sheet'!C17 -> 8 | E10: ='Balance sheet'!E17-'Balance sheet'!D17 -> 6
A11: Cash flow from operations | B11: =SUM(B6:B10) -> -2 | C11: =SUM(C6:C10) -> -6.2722513 | D11: =SUM(D6:D10) -> 67.639264 | E11: =SUM(E6:E10) -> 112.62098
A12: Less investment | B12: =-Operations!B16 -> -400 | C12: =-Operations!C16 -> -100 | D12: =-Operations!D16 -> -100 | E12: =-Operations!E16 -> -100
A13: Cash flow from operations and invests | B13: =B11+B12 -> -402 | C13: =C11+C12 -> -106.27225 | D13: =D11+D12 -> -32.360736 | E13: =E11+E12 -> 12.620975
A14: Plus net new equity capital raised | B14: =Financing!B12 -> 300 | C14: =Financing!C12 -> 0 | D14: =Financing!D12 -> 0 | E14: =Financing!E12 -> 0
A15: Less dividends paid | B15: 0 | C15: =-Financing!C13 -> 0 | D15: =-Financing!D13 -> 0 | E15: =-Financing!E13 -> 0
A16: Plus net new long-term debt | B16: =Financing!B9 -> 200 | C16: =Financing!C9-Financing!B9 -> 0 | D16: =Financing!D9-Financing!C9 -> 0 | E16: =Financing!E9-Financing!D9 -> 0
A17: Plus net new bank borrowings | B17: =Financing!B10 -> 0 | C17: =Financing!C10-Financing!B10 -> 28.272251 | D17: =Financing!D10-Financing!C10 -> 40.360736 | E17: =Financing!E10-Financing!D10 -> -6.620975
A18: Cash flow from ops, invests, and fin | B18: =SUM(B13:B17) -> 98 | C18: =SUM(C13:C17) -> -78 | D18: =SUM(D13:D17) -> 8 | E18: =SUM(E13:E17) -> 6
A19: Beginning cash balance | B19: 0 | C19: =B20 -> 98 | D19: =C20 -> 20 | E19: =D20 -> 28
A20: Ending cash balance | B20: =B18+B19 -> 98 | C20: =C18+C19 -> 20 | D20: =D18+D19 -> 28 | E20: =E18+E19 -> 34
